{"PackageName":"trifenix.connect.search","PackageType":1,"GithubHttp":"https://github.com/trifenix/connect-search.git","GithubSsh":"git@github.com:trifenix/connect-search.git","Versions":[{"Branch":"master","LastUpdate":new Date(-62135596800000),"SemanticBaseVersion":{"Major":0,"Minor":8,"Patch":47},"PreReleaseLabel":"","Preview":0,"DependantRelease":false,"IsFeature":false,"Build":null},{"Branch":"master","LastUpdate":new Date(1614479092309),"SemanticBaseVersion":{"Major":0,"Minor":8,"Patch":48},"PreReleaseLabel":"","Preview":0,"DependantRelease":false,"IsFeature":false,"Build":"1868"}],"DependantVersions":[],"Dependencies":null}